ssec/__init__.py
ssec/common.py
ssec/constants.py
ssec/event.py
ssec/py.typed
ssec/streamer.py
ssec-4.2.4.dist-info/licenses/LICENSE
ssec-4.2.4.dist-info/METADATA
ssec-4.2.4.dist-info/WHEEL
ssec-4.2.4.dist-info/top_level.txt
ssec-4.2.4.dist-info/RECORD
