Metadata-Version: 2.4
Name: ssec
Version: 4.2.4
Summary: Synchronous and asynchronous library for Server Sent Event (SSE). 
Author-email: "J. Baudisch" <justin.baudisch@hsbi.de>
Maintainer-email: "J. Baudisch" <justin.baudisch@hsbi.de>
Project-URL: Repository, https://github.com/ReMi-HSBI/ssec
Keywords: Server Sent Event (SSE),SSE-Client
Classifier: Development Status :: 5 - Production/Stable
Classifier: Intended Audience :: Developers
Classifier: Topic :: Software Development
Classifier: Topic :: Communications
Classifier: Programming Language :: Python
Classifier: Programming Language :: Python :: 3.13
Classifier: Programming Language :: Python :: Implementation :: CPython
Classifier: Typing :: Typed
Requires-Python: >=3.12
License-File: LICENSE
Requires-Dist: httpx==0.28.1
Provides-Extra: dev
Requires-Dist: ruff==0.11.8; extra == "dev"
Requires-Dist: mypy==1.15.0; extra == "dev"
Requires-Dist: Sphinx==8.2.3; extra == "dev"
Requires-Dist: furo==2024.8.6; extra == "dev"
Dynamic: license-file
